<?xml version="1.0"?>
<Application name="framework" version="2.006.000">
	<!--
		v2.006.000
		*	@date:		2023.11.03
		*	@author:	jose.rebelo
		*	@comment:	Feature |  Add functions and options on fw.person.group to achieve selection by several parameters, and support getting person.rel.group accordingly. Add error codes.
	-->
	<Configuration>
		<Key name="message_id_context" value="neon.framework" />
	</Configuration>
	<Databases/>
	<Menus>
		<Menu role="Teacher" startuc="application" startnode="" event="E_INIT" description="manage_application" default="true" />
		<Menu role="Teacher" startuc="application" startnode="" event="init" description="manageScheduledTasks" default="true" />
		<Menu role="Teacher" startuc="log" startnode="" event="E_INIT" description="log" />
	</Menus>
</Application>